fail2bangeolocation/__init__.py
fail2bangeolocation/cli.py
fail2bangeolocation/application/__init__.py
fail2bangeolocation/application/location.py
fail2bangeolocation/crosscutting/__init__.py
fail2bangeolocation/crosscutting/condition_messages.py
fail2bangeolocation/crosscutting/constants.py
fail2bangeolocation/crosscutting/strings.py
fail2bangeolocation/domain/__init__.py
fail2bangeolocation/domain/country.py
fail2bangeolocation/domain/fail2ban.py
fail2bangeolocation/domain/fail2banlog.py
fail2bangeolocation/domain/handlers/__init__.py
fail2bangeolocation/domain/handlers/error_handler.py
fail2bangeolocation/domain/handlers/exception_handler.py
fail2bangeolocation/domain/handlers/signal_handler.py
fail2bangeolocation/domain/utils/__init__.py
fail2bangeolocation/domain/utils/python_utils.py
fail2bangeolocation/domain/utils/system_utils.py
fail2bangeolocation/domain/utils/url_utils.py
fail2bangeolocation/infrastructure/__init__.py
fail2bangeolocation/infrastructure/reallyfreegeoip.py
fail2bangeolocation/presentation/__init__.py
fail2bangeolocation/presentation/cli_print.py
fail2bangeolocation/presentation/tag.py
fail2bangeolocation/presentation/utils/__init__.py
fail2bangeolocation/presentation/utils/screen.py
fail2bangeolocation-2.0.9.dist-info/METADATA
fail2bangeolocation-2.0.9.dist-info/WHEEL
fail2bangeolocation-2.0.9.dist-info/entry_points.txt
fail2bangeolocation-2.0.9.dist-info/licenses/LICENSE
fail2bangeolocation-2.0.9.dist-info/RECORD
