Metadata-Version: 2.3
Name: fail2bangeolocation
Version: 2.0.9
Summary: Shows geolocation of the IPs of the failed attempts recorded by fail2ban
Project-URL: Homepage, https://github.com/rubenhortas/fail2bangeolocation
Project-URL: Bug Tracker, https://github.com/rubenhortas/fail2bangeolocation/issues
Author-email: Rubén Hortas <rubenhortas@gmail.com>
License:                     GNU GENERAL PUBLIC LICENSE
License-File: LICENSE
Keywords: fail2ban,firewall,geolocation,montitoring,network,networking,security
Classifier: Development Status :: 5 - Production/Stable
Classifier: Environment :: Console
Classifier: Intended Audience :: Developers
Classifier: Intended Audience :: Information Technology
Classifier: Intended Audience :: System Administrators
Classifier: License :: OSI Approved :: GNU General Public License v3 (GPLv3)
Classifier: Operating System :: MacOS
Classifier: Operating System :: POSIX
Classifier: Programming Language :: Python :: 3 :: Only
Classifier: Topic :: Internet
Classifier: Topic :: Scientific/Engineering
Classifier: Topic :: Scientific/Engineering :: Information Analysis
Classifier: Topic :: Scientific/Engineering :: Visualization
Classifier: Topic :: Security
Classifier: Topic :: System :: Monitoring
Classifier: Topic :: System :: Networking
Classifier: Topic :: System :: Networking :: Firewalls
Requires-Python: >=3.0
Requires-Dist: colorama
Requires-Dist: requests
Requires-Dist: tqdm
Requires-Dist: urllib3
